LICENSE
MANIFEST.in
README.md
requirements.txt
setup.py
docs/source/conf.py
torchsar/__init__.py
torchsar/version.c
torchsar/version.py
torchsar.egg-info/PKG-INFO
torchsar.egg-info/SOURCES.txt
torchsar.egg-info/dependency_links.txt
torchsar.egg-info/requires.txt
torchsar.egg-info/top_level.txt
torchsar/autofocus/__init__.py
torchsar/autofocus/focusing.c
torchsar/autofocus/focusing.py
torchsar/autofocus/focusing.pyi
torchsar/autofocus/fourier_domain_optim.c
torchsar/autofocus/fourier_domain_optim.py
torchsar/autofocus/fourier_domain_optim.pyi
torchsar/autofocus/maximum_contrast.c
torchsar/autofocus/maximum_contrast.py
torchsar/autofocus/maximum_contrast.pyi
torchsar/autofocus/minimum_entropy.c
torchsar/autofocus/minimum_entropy.py
torchsar/autofocus/minimum_entropy.pyi
torchsar/autofocus/phase_error_model.c
torchsar/autofocus/phase_error_model.py
torchsar/autofocus/phase_error_model.pyi
torchsar/autofocus/phase_gradient.c
torchsar/autofocus/phase_gradient.py
torchsar/autofocus/phase_gradient.pyi
torchsar/calibration/__init__.py
torchsar/calibration/channel_process.c
torchsar/calibration/channel_process.py
torchsar/calibration/channel_process.pyi
torchsar/calibration/gain_compensation.c
torchsar/calibration/gain_compensation.py
torchsar/calibration/gain_compensation.pyi
torchsar/calibration/multilook_process.c
torchsar/calibration/multilook_process.py
torchsar/calibration/multilook_process.pyi
torchsar/evaluation/__init__.py
torchsar/evaluation/target_background.c
torchsar/evaluation/target_background.py
torchsar/evaluation/target_background.pyi
torchsar/imaging/__init__.py
torchsar/imaging/range_doppler_mftd.c
torchsar/imaging/range_doppler_mftd.py
torchsar/imaging/range_doppler_mftd.pyi
torchsar/misc/__init__.py
torchsar/misc/data.c
torchsar/misc/data.py
torchsar/misc/data.pyi
torchsar/misc/sardata.c
torchsar/misc/sardata.py
torchsar/misc/sardata.pyi
torchsar/misc/sarplat.c
torchsar/misc/sarplat.py
torchsar/misc/sarplat.pyi
torchsar/misc/visual.c
torchsar/misc/visual.py
torchsar/misc/visual.pyi
torchsar/module/__init__.py
torchsar/module/autofocus/__init__.py
torchsar/module/autofocus/autofocus.c
