Metadata-Version: 2.1
Name: torchsar
Version: 1.1.4
Summary: PyTorch Tools for Synthetic Aperture Radar.
Home-page: https://sar.iridescent.ink/
Download-URL: https://github.com/antsfamily/torchsar/
Author: Zhi Liu
Author-email: zhiliu.mind@gmail.com
License: MIT
Keywords: PyTorch,Synthetic Aperture Radar,Machine Learning,Deep Learning
License-File: LICENSE
